{
    "Badge": {
        "path": "Badge/Badge.md",
        "name": "Badge",
        "info": "### 说明\n\n-   这是 Badge 组件，用作角标展示\n-   支持点状角标\n-   预设部分颜色和角标位置\n-   不传 children 时会将角标单独展示，可用来作标记\n-   角标的 zIndex 默认为 9，无 children 时无 zIndex\n\n### 演示\n\n#### 演示\n\n```js {\"codepath\": \"badge.jsx\"}\n```\n\n#### placement - 位置\n\n```js {\"codepath\": \"placement.jsx\"}\n```\n\n#### dot - 显示为点\n\n```js {\"codepath\": \"dot.jsx\"}\n```\n\n#### hideWhenZero - 为 0 时自动隐藏\n\n```js {\"codepath\": \"hideWhenZero.jsx\"}\n```\n\n#### maxValue - 最大值\n\n```js {\"codepath\": \"maxValue.jsx\"}\n```\n\n#### value - 自定义内容\n\n```js {\"codepath\": \"value.jsx\"}\n```\n\n#### color - 预设颜色\n\n```js {\"codepath\": \"color.jsx\"}\n```\n\n#### badgeStyle - 自定义样式\n\n```js {\"codepath\": \"badgeStyle.jsx\"}\n```\n\n#### 无内容时展示\n\n```js {\"codepath\": \"noneContent.jsx\"}\n```\n\n#### 案例展示\n\n```js {\"codepath\": \"demo.jsx\"}\n```\n"
    },
    "Bubble": {
        "path": "Badge/Bubble.md",
        "name": "Bubble",
        "info": "### 说明\n\n-   这是 Bubble 组件，特殊的角标样式提示\n\n### 演示\n\n#### 演示\n\n```js {\"codepath\": \"bubble.jsx\"}\n```\n"
    }
}
